i2c_controller.v
`timescale 1ns / 1ps

module i2c_controller (
    input wire clk,
    input wire rst,
    input wire [6:0] addr,
    input wire [7:0] wdata,
    input wire enable,
    input wire rw, // 1 for read, 0 for write

    output reg [7:0] data_out,
    output wire ready,

    inout wire i2c_sda,
    inout wire i2c_scl
);

// FSM states
localparam IDLE        = 4'd0;
localparam START       = 4'd1;
localparam ADDRESS     = 4'd2;
localparam READ_ACK    = 4'd3;
localparam WRITE_DATA  = 4'd4;
localparam WRITE_ACK   = 4'd5;
localparam READ_DATA   = 4'd6;
localparam READ_ACK2   = 4'd7;
localparam STOP        = 4'd8;

reg [3:0] state;
reg [2:0] counter;

reg [7:0] saved_data;
reg [7:0] saved_addr;

reg sda_out;
reg write_enable;
reg i2c_scl_enable;
reg i2c_clk;

// Generate slower I2C clock using clock divider
reg [7:0] clk_divider;
always @(posedge clk or posedge rst) begin
    if (rst) begin
        clk_divider <= 0;
        i2c_clk <= 0;
    end else begin
        clk_divider <= clk_divider + 1;
        if (clk_divider == 100) begin
            i2c_clk <= ~i2c_clk;
            clk_divider <= 0;
        end
    end
end

// Ready signal
assign ready = (~rst) && (state == IDLE);

// i2c_scl control
assign i2c_scl = i2c_scl_enable ? i2c_clk : 1'bz;

// i2c_sda control
assign i2c_sda = write_enable ? sda_out : 1'bz;

// SCL enable logic
always @(negedge i2c_clk or posedge rst) begin
    if (rst) begin
        i2c_scl_enable <= 0;
    end else begin
        if ((state == IDLE) || (state == START) || (state == STOP))
            i2c_scl_enable <= 0;
        else
            i2c_scl_enable <= 1;
    end
end

// FSM
always @(posedge i2c_clk or posedge rst) begin
    if (rst) begin
        state <= IDLE;
        data_out <= 8'b0;
        counter <= 3'd7;
    end else begin
        case (state)
            IDLE: begin
                if (enable) begin
                    saved_addr <= {addr, rw};
                    saved_data <= wdata;
                    state <= START;
                end
            end

            START: begin
                counter <= 3'd7;
                state <= ADDRESS;
            end

            ADDRESS: begin
                if (counter == 0) state <= READ_ACK;
                else counter <= counter - 1;
            end

            READ_ACK: begin
                if (i2c_sda == 0) begin
                    counter <= 3'd7;
                    if (saved_addr[0] == 0) state <= WRITE_DATA;
                    else state <= READ_DATA;
                end else state <= STOP;
            end

            WRITE_DATA: begin
                if (counter == 0) state <= READ_ACK2;
                else counter <= counter - 1;
            end

            READ_DATA: begin
                data_out[counter] <= i2c_sda;
                if (counter == 0) state <= WRITE_ACK;
                else counter <= counter - 1;
            end

            WRITE_ACK: begin
                state <= STOP;
            end

            READ_ACK2: begin
                state <= STOP;
            end

            STOP: begin
                state <= IDLE;
            end

            default: state <= IDLE;
        endcase
    end
end

// SDA driver logic
always @(negedge i2c_clk or posedge rst) begin
    if (rst) begin
        write_enable <= 1;
        sda_out <= 1;
    end else begin
        case (state)
            START: begin
                write_enable <= 1;
                sda_out <= 0;
            end
            ADDRESS: begin
                sda_out <= saved_addr[counter];
            end
            READ_ACK: begin
                write_enable <= 0;
            end
            WRITE_DATA: begin
                write_enable <= 1;
                sda_out <= saved_data[counter];
            end
            READ_DATA: begin
                write_enable <= 0;
            end
            WRITE_ACK: begin
                write_enable <= 1;
                sda_out <= 0;
            end
            STOP: begin
                write_enable <= 1;
                sda_out <= 1;
            end
        endcase
    end
end

endmodule

tb_i2c_controller.v
`timescale 1ns / 1ps

module tb_i2c_controller;

reg clk;
reg rst;
reg [6:0] addr;
reg [7:0] wdata;
reg enable;
reg rw;

wire [7:0] data_out;
wire ready;
wire i2c_sda;
wire i2c_scl;

// Instantiate DUT
i2c_controller uut (
    .clk(clk),
    .rst(rst),
    .addr(addr),
    .wdata(wdata),
    .enable(enable),
    .rw(rw),
    .data_out(data_out),
    .ready(ready),
    .i2c_sda(i2c_sda),
    .i2c_scl(i2c_scl)
);

// Clock generation
always #5 clk = ~clk;

// Initial block
initial begin
    $dumpfile("i2c.vcd");
    $dumpvars(0, tb_i2c_controller);

    clk = 0;
    rst = 1;
    addr = 7'b1010101;
    wdata = 8'hA5;
    enable = 0;
    rw = 0; // Write

    #20;
    rst = 0;
    #20;
    enable = 1;

    // Hold enable for some cycles
    #50;
    enable = 0;

    // Wait for transaction to finish
    #1000;
    $finish;
end

endmodule

i2c.vcd
$date
	Mon May 26 15:18:25 2025
$end
$version
	Icarus Verilog
$end
$timescale
	1ps
$end
$scope module tb_i2c_controller $end
$var wire 1 ! ready $end
$var wire 1 " i2c_sda $end
$var wire 1 # i2c_scl $end
$var wire 8 $ data_out [7:0] $end
$var reg 7 % addr [6:0] $end
$var reg 1 & clk $end
$var reg 1 ' enable $end
$var reg 1 ( rst $end
$var reg 1 ) rw $end
$var reg 8 * wdata [7:0] $end
$scope module uut $end
$var wire 7 + addr [6:0] $end
$var wire 1 & clk $end
$var wire 1 ' enable $end
$var wire 1 ! ready $end
$var wire 1 ( rst $end
$var wire 1 ) rw $end
$var wire 8 , wdata [7:0] $end
$var wire 1 " i2c_sda $end
$var wire 1 # i2c_scl $end
$var parameter 4 - ADDRESS $end
$var parameter 4 . IDLE $end
$var parameter 4 / READ_ACK $end
$var parameter 4 0 READ_ACK2 $end
$var parameter 4 1 READ_DATA $end
$var parameter 4 2 START $end
$var parameter 4 3 STOP $end
$var parameter 4 4 WRITE_ACK $end
$var parameter 4 5 WRITE_DATA $end
$var reg 8 6 clk_divider [7:0] $end
$var reg 3 7 counter [2:0] $end
$var reg 8 8 data_out [7:0] $end
$var reg 1 9 i2c_clk $end
$var reg 1 : i2c_scl_enable $end
$var reg 8 ; saved_addr [7:0] $end
$var reg 8 < saved_data [7:0] $end
$var reg 1 = sda_out $end
$var reg 4 > state [3:0] $end
$var reg 1 ? write_enable $end
$upscope $end
$upscope $end
$enddefinitions $end
$comment Show the parameter values. $end
$dumpall
b100 5
b101 4
b1000 3
b1 2
b110 1
b111 0
b11 /
b0 .
b10 -
$end
#0
$dumpvars
1?
b0 >
1=
bx <
bx ;
0:
09
b0 8
b111 7
b0 6
b10100101 ,
b1010101 +
b10100101 *
0)
1(
0'
0&
b1010101 %
b0 $
z#
1"
0!
$end
#5000
1&
#10000
0&
#15000
1&
#20000
1!
0&
0(
#25000
b1 6
1&
#30000
0&
#35000
b10 6
1&
#40000
0&
1'
#45000
b11 6
1&
#50000
0&
#55000
b100 6
1&
#60000
0&
#65000
b101 6
1&
#70000
0&
#75000
b110 6
1&
#80000
0&
#85000
b111 6
1&
#90000
0&
0'
#95000
b1000 6
1&
#100000
0&
#105000
b1001 6
1&
#110000
0&
#115000
b1010 6
1&
#120000
0&
#125000
b1011 6
1&
#130000
0&
#135000
b1100 6
1&
#140000
0&
#145000
b1101 6
1&
#150000
0&
#155000
b1110 6
1&
#160000
0&
#165000
b1111 6
1&
#170000
0&
#175000
b10000 6
1&
#180000
0&
#185000
b10001 6
1&
#190000
0&
#195000
b10010 6
1&
#200000
0&
#205000
b10011 6
1&
#210000
0&
#215000
b10100 6
1&
#220000
0&
#225000
b10101 6
1&
#230000
0&
#235000
b10110 6
1&
#240000
0&
#245000
b10111 6
1&
#250000
0&
#255000
b11000 6
1&
#260000
0&
#265000
b11001 6
1&
#270000
0&
#275000
b11010 6
1&
#280000
0&
#285000
b11011 6
1&
#290000
0&
#295000
b11100 6
1&
#300000
0&
#305000
b11101 6
1&
#310000
0&
#315000
b11110 6
1&
#320000
0&
#325000
b11111 6
1&
#330000
0&
#335000
b100000 6
1&
#340000
0&
#345000
b100001 6
1&
#350000
0&
#355000
b100010 6
1&
#360000
0&
#365000
b100011 6
1&
#370000
0&
#375000
b100100 6
1&
#380000
0&
#385000
b100101 6
1&
#390000
0&
#395000
b100110 6
1&
#400000
0&
#405000
b100111 6
1&
#410000
0&
#415000
b101000 6
1&
#420000
0&
#425000
b101001 6
1&
#430000
0&
#435000
b101010 6
1&
#440000
0&
#445000
b101011 6
1&
#450000
0&
#455000
b101100 6
1&
#460000
0&
#465000
b101101 6
1&
#470000
0&
#475000
b101110 6
1&
#480000
0&
#485000
b101111 6
1&
#490000
0&
#495000
b110000 6
1&
#500000
0&
#505000
b110001 6
1&
#510000
0&
#515000
b110010 6
1&
#520000
0&
#525000
b110011 6
1&
#530000
0&
#535000
b110100 6
1&
#540000
0&
#545000
b110101 6
1&
#550000
0&
#555000
b110110 6
1&
#560000
0&
#565000
b110111 6
1&
#570000
0&
#575000
b111000 6
1&
#580000
0&
#585000
b111001 6
1&
#590000
0&
#595000
b111010 6
1&
#600000
0&
#605000
b111011 6
1&
#610000
0&
#615000
b111100 6
1&
#620000
0&
#625000
b111101 6
1&
#630000
0&
#635000
b111110 6
1&
#640000
0&
#645000
b111111 6
1&
#650000
0&
#655000
b1000000 6
1&
#660000
0&
#665000
b1000001 6
1&
#670000
0&
#675000
b1000010 6
1&
#680000
0&
#685000
b1000011 6
1&
#690000
0&
#695000
b1000100 6
1&
#700000
0&
#705000
b1000101 6
1&
#710000
0&
#715000
b1000110 6
1&
#720000
0&
#725000
b1000111 6
1&
#730000
0&
#735000
b1001000 6
1&
#740000
0&
#745000
b1001001 6
1&
#750000
0&
#755000
b1001010 6
1&
#760000
0&
#765000
b1001011 6
1&
#770000
0&
#775000
b1001100 6
1&
#780000
0&
#785000
b1001101 6
1&
#790000
0&
#795000
b1001110 6
1&
#800000
0&
#805000
b1001111 6
1&
#810000
0&
#815000
b1010000 6
1&
#820000
0&
#825000
b1010001 6
1&
#830000
0&
#835000
b1010010 6
1&
#840000
0&
#845000
b1010011 6
1&
#850000
0&
#855000
b1010100 6
1&
#860000
0&
#865000
b1010101 6
1&
#870000
0&
#875000
b1010110 6
1&
#880000
0&
#885000
b1010111 6
1&
#890000
0&
#895000
b1011000 6
1&
#900000
0&
#905000
b1011001 6
1&
#910000
0&
#915000
b1011010 6
1&
#920000
0&
#925000
b1011011 6
1&
#930000
0&
#935000
b1011100 6
1&
#940000
0&
#945000
b1011101 6
1&
#950000
0&
#955000
b1011110 6
1&
#960000
0&
#965000
b1011111 6
1&
#970000
0&
#975000
b1100000 6
1&
#980000
0&
#985000
b1100001 6
1&
#990000
0&
#995000
b1100010 6
1&
#1000000
0&
#1005000
b1100011 6
1&
#1010000
0&
#1015000
b1100100 6
1&
#1020000
0&
#1025000
19
b0 6
1&
#1030000
0&
#1035000
b1 6
1&
#1040000
0&
#1045000
b10 6
1&
#1050000
0&
#1055000
b11 6
1&
#1060000
0&
#1065000
b100 6
1&
#1070000
0&
#1075000
b101 6
1&
#1080000
0&
#1085000
b110 6
1&
